MANIFEST.in
license
readme.md
setup.cfg
setup.py
celery_aws_xray_sdk_extension/__init__.py
celery_aws_xray_sdk_extension/handlers.py
celery_aws_xray_sdk_extension.egg-info/PKG-INFO
celery_aws_xray_sdk_extension.egg-info/SOURCES.txt
celery_aws_xray_sdk_extension.egg-info/dependency_links.txt
celery_aws_xray_sdk_extension.egg-info/requires.txt
celery_aws_xray_sdk_extension.egg-info/top_level.txt