Metadata-Version: 2.1
Name: celery-aws-xray-sdk-extension
Version: 0.1.2
Summary: Extension for AWS X-Ray SDK which enables tracing of Celery tasks
Home-page: https://github.com/druids/celery-aws-xray-sdk-extension
Author: Radim Sückr
Author-email: kontakt@radimsuckr.cz
License: MIT
Classifier: Development Status :: 3 - Alpha
Classifier: Framework :: Celery
Classifier: License :: OSI Approved :: MIT License
Requires-Python: >=3.6
